Metadata-Version: 2.1
Name: Arest7
Version: 0.0.1
Summary: For testing
Home-page: UNKNOWN
Author: Ken Ryuguji
Author-email: behruzbekabdumutalov@Gmail.com
License: UNKNOWN
Keywords: python,python banner,art
Platform: UNKNOWN
Classifier: Development Status :: 1 - Planning
Classifier: Intended Audience :: Developers
Classifier: Programming Language :: Python :: 3
